promptify_summary/__init__.py
promptify_summary/main.py
promptify_summary/prompts.py
promptify_summary-2025.12.21103043.dist-info/METADATA
promptify_summary-2025.12.21103043.dist-info/WHEEL
promptify_summary-2025.12.21103043.dist-info/top_level.txt
promptify_summary-2025.12.21103043.dist-info/RECORD
