Metadata-Version: 2.4
Name: promptify-summary
Version: 2025.12.21103043
Summary: A new package would process text inputs, like video titles or descriptions, to generate structured summaries using an LLM. It would take a user-provided text string (e.g., a headline or query) and ret
Author-email: promptify-summary <hi@eugene.plus>
License: MIT
Project-URL: Homepage, https://github.com/chigwell/promptify-summary
Requires-Python: >=3.9
Requires-Dist: langchain-llm7>=0.0.0
Requires-Dist: llmatch-messages>=0.0.0
Requires-Dist: langchain-core>=0.3.0
